silverstripe_installer/__init__.py
silverstripe_installer/__main__.py
silverstripe_installer/silverstripeinstaller.py
silverstripe_installer/tzogitlab.py
tzo_silverstripe_installer-0.3.1.dist-info/METADATA
tzo_silverstripe_installer-0.3.1.dist-info/RECORD
tzo_silverstripe_installer-0.3.1.dist-info/WHEEL
tzo_silverstripe_installer-0.3.1.dist-info/entry_points.txt
tzo_silverstripe_installer-0.3.1.dist-info/top_level.txt
