Metadata-Version: 2.1
Name: tzo-silverstripe-installer
Version: 0.3.1
Summary: Automation script to create new Silverstripe site.
Home-page: http://git.timezoneone.com/timezoneone/tzo-silverstripe-installer
Author: Shawn Lin
Author-email: shawn@timezoneone.com
License: MIT
Keywords: timezoneone tzo silverstripe
Platform: UNKNOWN
Classifier: Development Status :: 4 - Beta
Classifier: Intended Audience :: Developers
Classifier: License :: OSI Approved :: MIT License
Classifier: Topic :: Software Development :: Libraries :: Python Modules
Classifier: Programming Language :: Python :: 3.5
Classifier: Programming Language :: Python :: 3.6
Requires-Dist: requests
